helpful/__init__.py
helpful/apps.py
helpful/easy_email.py
helpful/fields.py
helpful/middleware.py
helpful/signals.py
helpful/sms.py
helpful/locale/de/LC_MESSAGES/django.mo
helpful/locale/de/LC_MESSAGES/django.po
helpful/locale/ru/LC_MESSAGES/django.mo
helpful/locale/ru/LC_MESSAGES/django.po
helpful/templates/helpful/breadcrumbs.html
helpful/templatetags/__init__.py
helpful/templatetags/abs_puth.py
helpful/templatetags/breadcrumbs.py
helpful/templatetags/helpful.py
helpful/templatetags/image2base64.py
helpful/templatetags/object_dict.py
helpful/templatetags/render.py
django_helpful-1.6.4.dist-info/METADATA
django_helpful-1.6.4.dist-info/WHEEL
django_helpful-1.6.4.dist-info/top_level.txt
django_helpful-1.6.4.dist-info/RECORD
