Metadata-Version: 2.1
Name: django-helpful
Version: 1.6.4
Summary: Django helpful things
Home-page: https://github.com/Baltrunas/django-helpful
Author: Stanislav Baltrunas
Author-email: stanislav@baltrunas.ru
License: BSD
Classifier: Development Status :: 4 - Beta
Classifier: Environment :: Web Environment
Classifier: Intended Audience :: Developers
Classifier: License :: OSI Approved :: BSD License
Classifier: Operating System :: OS Independent
Classifier: Programming Language :: Python
Classifier: Framework :: Django
Requires-Python: >=2.6, <4
